Tugas_Tutorial/Tugas_Tutorial_1/TugasTutorial1.v
module AND_Gate32bit(
    input [31:0] A,
    input [31:0] B,
    output [31:0] HasilANDLogic
);

    assign HasilANDLogic = A & B;

endmodule

module OR_Gate32bit(
    input [31:0] A,
    input [31:0] B,
    output [31:0] HasilORLogic
);

    assign HasilORLogic = A | B;

endmodule

module XOR_Gate32bit(
    input [31:0] A,
    input [31:0] B,
    output [31:0] HasilXORLogic
);

    assign HasilXORLogic = A ^ B;

endmodule

module INVERTER_32bit(
    input [31:0] A,
    output [31:0] HasilINVERTER
);

    assign HasilINVERTER = ~A;

endmodule

Tugas Tutorial/tb_INVERTER_32bit.v
`timescale 1ns/1ps

module tb_INVERTER_32bit();
    reg [31:0] A;
    wire [31:0] HasilINVERTER;

    INVERTER_32bit uut(.A(A), .HasilINVERTER(HasilINVERTER));
    initial begin
        $dumpfile("INVERTER_32bit.vcd");
        $dumpvars(0, tb_INVERTER_32bit);
        $monitor("A = %h,  HasilINVERTER = %h,", A, HasilINVERTER); 

        A = 32'h0000_0000; #1;
        A = 32'h0000_FFFF; #1;
        A = 32'hFFFF_FFFF; #1;
        A = 32'hAAAA_0000; #1;
        A = 32'hAAAA_AAAA; #1;
        A = 32'h0F0F_0000; #1;
        A = 32'hFFFF_0000; #1;
        A = 32'hF0F0_F0F0; #1;
        A = 32'h1234_5678; #1;
        A = 32'h9ABC_DEF0; #1;

        $finish;
    end

endmodule

Tugas Tutorial/INVERTER_32bit.vcd
$date
	Sun Aug 30 13:53:10 2026
$end
$version
	Icarus Verilog
$end
$timescale
	1ps
$end
$scope module tb_INVERTER_32bit $end
$var wire 32 ! HasilINVERTER [31:0] $end
$var reg 32 " A [31:0] $end
$scope module uut $end
$var wire 32 # A [31:0] $end
$var wire 32 $ HasilINVERTER [31:0] $end
$upscope $end
$upscope $end
$enddefinitions $end
$comment Show the parameter values. $end
$dumpall
$end
#0
$dumpvars
b11111111111111111111111111111111 $
b0 #
b0 "
b11111111111111111111111111111111 !
$end
#1000
b11111111111111110000000000000000 !
b11111111111111110000000000000000 $
b1111111111111111 "
b1111111111111111 #
#2000
b0 !
b0 $
b11111111111111111111111111111111 "
b11111111111111111111111111111111 #
#3000
b1010101010101011111111111111111 !
b1010101010101011111111111111111 $
b10101010101010100000000000000000 "
b10101010101010100000000000000000 #
#4000
b1010101010101010101010101010101 !
b1010101010101010101010101010101 $
b10101010101010101010101010101010 "
b10101010101010101010101010101010 #
#5000
b11110000111100001111111111111111 !
b11110000111100001111111111111111 $
b1111000011110000000000000000 "
b1111000011110000000000000000 #
#6000
b1111111111111111 !
b1111111111111111 $
b11111111111111110000000000000000 "
b11111111111111110000000000000000 #
#7000
b1111000011110000111100001111 !
b1111000011110000111100001111 $
b11110000111100001111000011110000 "
b11110000111100001111000011110000 #
#8000
b11101101110010111010100110000111 !
b11101101110010111010100110000111 $
b10010001101000101011001111000 "
b10010001101000101011001111000 #
#9000
b1100101010000110010000100001111 !
b1100101010000110010000100001111 $
b10011010101111001101111011110000 "
b10011010101111001101111011110000 #
