Tugas_Tutorial/Tugas_Tutorial_1/TugasTutorial1.v
module AND_Gate32bit(
    input [31:0] A,
    input [31:0] B,
    output [31:0] HasilANDLogic
);

    assign HasilANDLogic = A & B;

endmodule

module OR_Gate32bit(
    input [31:0] A,
    input [31:0] B,
    output [31:0] HasilORLogic
);

    assign HasilORLogic = A | B;

endmodule

module XOR_Gate32bit(
    input [31:0] A,
    input [31:0] B,
    output [31:0] HasilXORLogic
);

    assign HasilXORLogic = A ^ B;

endmodule

module INVERTER_32bit(
    input [31:0] A,
    output [31:0] HasilINVERTER
);

    assign HasilINVERTER = ~A;

endmodule

Tugas_Tutorial/Tugas_Tutorial_1/tb_OR_Gate32bit.v
`timescale 1ns/1ps

module tb_OR_Gate32bit();
    reg [31:0] A, B;
    wire [31:0] HasilORLogic;

    OR_Gate32bit uut(.A(A), .B(B), .HasilORLogic(HasilORLogic));
    initial begin
        $dumpfile("OR_Gate32bit.vcd");
        $dumpvars(0, tb_OR_Gate32bit);
        $monitor("A = %h, B = %h, HasilORLogic = %h,", A, B, HasilORLogic); 

        A = 32'h0000_0000; B = 32'h0000_0000; #1;
        A = 32'hFFFF_FFFF; B = 32'hFFFF_FFFF; #1;
        A = 32'hFFFF_FFFF; B = 32'h0000_0000; #1;
        A = 32'hAAAA_AAAA; B = 32'h5555_5555; #1;
        A = 32'hAAAA_AAAA; B = 32'hAAAA_AAAA; #1;
        A = 32'hFFFF_0000; B = 32'h0000_FFFF; #1;
        A = 32'hFFFF_0000; B = 32'hFFFF_FFFF; #1;
        A = 32'hF0F0_F0F0; B = 32'h0F0F_0F0F; #1;
        A = 32'h1234_5678; B = 32'h8765_4321; #1;
        A = 32'h9ABC_DEF0; B = 32'hFFFF_0000; #1;

        $finish;
    end

endmodule

Tugas Tutorial/OR_Gate32bit.vcd
$date
	Sun Aug 30 13:53:10 2026
$end
$version
	Icarus Verilog
$end
$timescale
	1ps
$end
$scope module tb_OR_Gate32bit $end
$var wire 32 ! HasilORLogic [31:0] $end
$var reg 32 " A [31:0] $end
$var reg 32 # B [31:0] $end
$scope module uut $end
$var wire 32 $ A [31:0] $end
$var wire 32 % B [31:0] $end
$var wire 32 & HasilORLogic [31:0] $end
$upscope $end
$upscope $end
$enddefinitions $end
$comment Show the parameter values. $end
$dumpall
$end
#0
$dumpvars
b0 &
b0 %
b0 $
b0 #
b0 "
b0 !
$end
#1000
b11111111111111111111111111111111 !
b11111111111111111111111111111111 &
b11111111111111111111111111111111 #
b11111111111111111111111111111111 %
b11111111111111111111111111111111 "
b11111111111111111111111111111111 $
#2000
b0 #
b0 %
#3000
b1010101010101010101010101010101 #
b1010101010101010101010101010101 %
b10101010101010101010101010101010 "
b10101010101010101010101010101010 $
#4000
b10101010101010101010101010101010 !
b10101010101010101010101010101010 &
b10101010101010101010101010101010 #
b10101010101010101010101010101010 %
#5000
b11111111111111111111111111111111 !
b11111111111111111111111111111111 &
b1111111111111111 #
b1111111111111111 %
b11111111111111110000000000000000 "
b11111111111111110000000000000000 $
#6000
b11111111111111111111111111111111 #
b11111111111111111111111111111111 %
#7000
b1111000011110000111100001111 #
b1111000011110000111100001111 %
b11110000111100001111000011110000 "
b11110000111100001111000011110000 $
#8000
b10010111011101010101011101111001 !
b10010111011101010101011101111001 &
b10000111011001010100001100100001 #
b10000111011001010100001100100001 %
b10010001101000101011001111000 "
b10010001101000101011001111000 $
#9000
b11111111111111111101111011110000 !
b11111111111111111101111011110000 &
b11111111111111110000000000000000 #
b11111111111111110000000000000000 %
b10011010101111001101111011110000 "
b10011010101111001101111011110000 $
